datacatalog_tag_template_exporter/__init__.py
datacatalog_tag_template_exporter/constant.py
datacatalog_tag_template_exporter/datacatalog_entity_factory.py
datacatalog_tag_template_exporter/datacatalog_facade.py
datacatalog_tag_template_exporter/datacatalog_tag_template_exporter_cli.py
datacatalog_tag_template_exporter/tag_template_datasource_exporter.py
datacatalog_tag_template_exporter-0.1.2.dist-info/AUTHORS.rst
datacatalog_tag_template_exporter-0.1.2.dist-info/LICENSE
datacatalog_tag_template_exporter-0.1.2.dist-info/METADATA
datacatalog_tag_template_exporter-0.1.2.dist-info/WHEEL
datacatalog_tag_template_exporter-0.1.2.dist-info/entry_points.txt
datacatalog_tag_template_exporter-0.1.2.dist-info/top_level.txt
datacatalog_tag_template_exporter-0.1.2.dist-info/RECORD
